[
  {
    "type": "Coding",
    "items": [
      {
        "name": "GitHub",
        "href": "https://github.com/",
        "description": "Simple repository management."
      },
      {
        "name": "Postman",
        "href": "https://www.postman.com/",
        "description": "Build and test APIs."
      },
      {
        "name": "VS Code",
        "href": "https://code.visualstudio.com/",
        "description": "Modern IDE and code editor."
      },
      {
        "name": "Continue",
        "href": "https://continue.dev/",
        "description": "Autopilot for software development."
      },
      {
        "name": "Anima App",
        "href": "https://animaapp.com/",
        "description": "AI design to code."
      },
      {
        "name": "Subframe",
        "href": "https://subframe.com/",
        "description": "Export your designs to React code."
      }
    ]
  },
  {
    "type": "No-code",
    "items": [
      {
        "name": "Xano",
        "href": "https://xano.com/",
        "description": "Backend development without writing code."
      },
      {
        "name": "Bubble",
        "href": "https://bubble.io",
        "description": "The easiest way to build web apps without code."
      },
      {
        "name": "Softr",
        "href": "https://softr.io",
        "description": "Build custom apps from simple databases."
      },
      {
        "name": "Zapier",
        "href": "https://zapier.com",
        "description": "Automate your workflows. Fast."
      },
      {
        "name": "Make",
        "href": "https://make.com",
        "description": "Connect and integrate apps to your software."
      },
      {
        "name": "Adalo",
        "href": "https://adalo.com",
        "description": "Build and launch mobile apps. No-code required."
      },
      {
        "name": "Flutterflow",
        "href": "https://flutterflow.io",
        "description": "Low code tool to build beautiful, modern apps."
      },
      {
        "name": "Airtable",
        "href": "https://airtable.com",
        "description": "Powerful database for your apps"
      },
      {
        "name": "Tally",
        "href": "https://tally.so",
        "description": "The simplest way to create forms."
      }
    ]
  },
  {
    "type": "Productivity",
    "items": [
      {
        "name": "Google Meet",
        "href": "https://meet.google.com/",
        "description": "Video conferencing and communication tool."
      },
      {
        "name": "Loom",
        "href": "https://loom.com/",
        "description": "Beautiful, collaborative screen recordings"
      },
      {
        "name": "Linear",
        "href": "https://linear.app/",
        "description": "Simple, focused issue tracking."
      },
      {
        "name": "Notion",
        "href": "https://www.notion.so/",
        "description": "Documents with endless possibilities."
      },
      {
        "name": "Pitch",
        "href": "https://pitch.com/",
        "description": "Modern, collaborative presentation tool."
      },
      {
        "name": "Slack",
        "href": "https://slack.com/",
        "description": "The platform for teamwork."
      },
      {
        "name": "Arcade",
        "href": "https://arcade.software",
        "description": "Effortless, beautiful interactive demos."
      }
    ]
  },
  {
    "type": "Analytics",
    "items": [
      {
        "name": "Google Analytics",
        "href": "https://dovetailapp.com/",
        "description": "Effective web analytics."
      },
      {
        "name": "Mixpanel",
        "href": "https://www.mixpanel.com/",
        "description": "Product analytics for mobile and web."
      },
      {
        "name": "June",
        "href": "https://june.so",
        "description": "Product analytics for your business."
      }
    ]
  },
  {
    "type": "Mailing",
    "items": [
      {
        "name": "Mailchimp",
        "href": "https://mailchimp.com/",
        "description": "Marketing, automation and email platform."
      },
      {
        "name": "Resend",
        "href": "https://resend.com",
        "description": "Email for developers"
      },
      {
        "name": "Beehiiv",
        "href": "https://beehiiv.com",
        "description": "Newsletter platform for growth."
      },
      {
        "name": "Really Good Emails",
        "href": "https://reallygoodemails.com/",
        "description": "Endless email design and content inspiration."
      },
      {
        "name": "AWS SES",
        "href": "https://aws.amazon.com/ses/",
        "description": "Transactional and marketing email APIs"
      }
    ]
  }
]
